dptools/__init__.py
dptools/env.py
dptools/hpc.py
dptools/utils.py
dptools/z.py
dptools/cli/__init__.py
dptools/cli/convert.py
dptools/cli/get.py
dptools/cli/info.py
dptools/cli/input.py
dptools/cli/parity.py
dptools/cli/reset.py
dptools/cli/run.py
dptools/cli/sample.py
dptools/cli/set.py
dptools/cli/shake.py
dptools/cli/train.py
dptools/simulate/__init__.py
dptools/simulate/calculator.py
dptools/simulate/lammps_io.py
dptools/simulate/parameter_sets.yaml
dptools/simulate/parameters.py
dptools/simulate/simulations.py
dptools/train/__init__.py
dptools/train/ensemble.py
dptools/train/in.json
dptools/train/input.py
dptools/train/parity.py
dpmdtools-1.1.2.dist-info/LICENSE
dpmdtools-1.1.2.dist-info/METADATA
dpmdtools-1.1.2.dist-info/WHEEL
dpmdtools-1.1.2.dist-info/entry_points.txt
dpmdtools-1.1.2.dist-info/top_level.txt
dpmdtools-1.1.2.dist-info/RECORD
