Metadata-Version: 2.1
Name: dpmdtools
Version: 1.1.2
Summary: DPTools: CLI toolkit and python library for working with deepmd-kit.
Home-page: https://github.com/tysours/DPTools
Maintainer: Ty Sours
Maintainer-email: tsours@ucdavis.edu
License: MIT
Project-URL: Documentation, http://dptools.readthedocs.io/
Project-URL: Source, https://github.com/tysours/DPTools
Project-URL: Tracker, https://github.com/tysours/DPTools/issues
Classifier: Development Status :: 3 - Alpha
Classifier: License :: OSI Approved :: MIT License
Classifier: Operating System :: OS Independent
Classifier: Programming Language :: Python :: 3
Classifier: Intended Audience :: Science/Research
Classifier: Topic :: Scientific/Engineering :: Chemistry
Requires-Python: >=3.6
License-File: LICENSE
Requires-Dist: ase
Requires-Dist: scikit-learn
Requires-Dist: python-dotenv
Requires-Dist: ruamel.yaml
